merdb-0.0.2.dist-info/METADATA
merdb-0.0.2.dist-info/WHEEL
merdb/__init__.py
merdb/api/__init__.py
merdb/api/base.py
merdb/api/common.py
merdb/api/pipe.py
merdb/api/tacit.py
merdb/api/tacit_interactive.py
merdb/core.py
merdb/interactive.py
merdb/qlang.py
merdb/resource/__init__.py
merdb/resource/modin_resource.py
merdb-0.0.2.dist-info/RECORD
