Metadata-Version: 2.1
Name: merdb
Version: 0.0.2
Summary: Datastore supporting merql
Author-Email: Rajiv Abraham <rajiv.abraham@gmail.com>
License: MIT
Requires-Python: >=3.10
Requires-Dist: modin[ray]>=0.23.0
Requires-Dist: sspipe>=0.1.17
